twind/__init__.py
twind/__version__.py
twind/downloader.py
twind/models.py
twind/plotter.py
twind/sampler.py
twind/simulation.py
twind/tigress_tools.py
twind-1.1.2.dist-info/LICENSE
twind-1.1.2.dist-info/METADATA
twind-1.1.2.dist-info/WHEEL
twind-1.1.2.dist-info/top_level.txt
twind-1.1.2.dist-info/RECORD
