Metadata-Version: 2.1
Name: twind
Version: 1.1.2
Summary: Twind: TIGRESS Wind Launching Model and Sampler
Home-page: https://twind.readthedocs.io
Author: Chang-Goo Kim
Author-email: changgookim@gmail.com
License: MIT
Project-URL: Documentation, https://twind.readthedocs.io
Project-URL: Source Code, https://github.com/changgoo/Twind
Keywords: galactic wind
Platform: Windows
Platform: Mac OS-X
Platform: Linux
Platform: Unix
Classifier: Development Status :: 5 - Production/Stable
Classifier: Intended Audience :: Developers
Classifier: Intended Audience :: Science/Research
Classifier: License :: OSI Approved :: MIT License
Classifier: Natural Language :: English
Classifier: Operating System :: OS Independent
Classifier: Programming Language :: Python
Requires-Python: >=3.6, <4
License-File: LICENSE
Requires-Dist: numpy (>=1.18)
Requires-Dist: xarray (>=0.15)
Requires-Dist: matplotlib (>=3.0)
Requires-Dist: scipy (>=1.4)
Requires-Dist: astropy
Requires-Dist: seaborn (>=0.10)
Requires-Dist: cmasher (>=1.4)
